multiplexers/16to1/mux16to1.v
`timescale 1ns/1ns

module mux16to1 (
    input [15:0]A,
    input enable,
    input [3:0]sel,
    output Y
);
    wire [3:0]sel_not;
    wire [15:0]X;
    assign sel_not = ~ sel;
    and G1 (X[0],A[0],sel_not[0],sel_not[1],sel_not[2],sel_not[3],enable);
    and G2 (X[1],A[1],sel[0],sel_not[1],sel_not[2],sel_not[3],enable);
    and G3 (X[2],A[2],sel_not[0],sel[1],sel_not[2],sel_not[3],enable);
    and G4 (X[3],A[3],sel[0],sel[1],sel_not[2],sel_not[3],enable);   

    and G5 (X[4],A[4],sel_not[0],sel_not[1],sel[2],sel_not[3],enable);
    and G6 (X[5],A[5],sel[0],sel_not[1],sel[2],sel_not[3],enable);
    and G7 (X[6],A[6],sel_not[0],sel[1],sel[2],sel_not[3],enable);
    and G8 (X[7],A[7],sel[0],sel[1],sel[2],sel_not[3],enable);

    and G9 (X[8],A[8],sel_not[0],sel_not[1],sel_not[2],sel[3],enable);
    and G10 (X[9],A[9],sel[0],sel_not[1],sel_not[2],sel[3],enable);
    and G11 (X[10],A[10],sel_not[0],sel[1],sel_not[2],sel[3],enable);
    and G12 (X[11],A[11],sel[0],sel[1],sel_not[2],sel[3],enable);   

    and G13 (X[12],A[12],sel_not[0],sel_not[1],sel[2],sel[3],enable);
    and G14 (X[13],A[13],sel[0],sel_not[1],sel[2],sel[3],enable);
    and G15 (X[14],A[14],sel_not[0],sel[1],sel[2],sel[3],enable);
    and G16 (X[15],A[15],sel[0],sel[1],sel[2],sel[3],enable);
     
    assign Y = |X;
endmodule

multiplexers/16to1/mux16to1_tb.v
`timescale 1ns/1ns
`include "mux16to1.v"

module decoder_tb ();
    reg [3:0]sel_t;
    reg enable_t;
    reg [15:0]a_t;
    wire y_t;
    mux16to1 uut(.A(a_t),.enable(enable_t),.sel(sel_t),.Y(y_t));
    initial begin
        $dumpfile("mux16to1_tb.vcd");
        $dumpvars(1,a_t,sel_t,enable_t,y_t);
        $monitor("%b %b %b",a_t,sel_t,y_t);
        a_t = 16'b1011_0111_0011_0111;
        sel_t = 4'b0000;
        enable_t = 1'b0;
        #10 enable_t = 1'b1;
        sel_t = 4'b0000;
        repeat(15)
        #10 sel_t = sel_t + 4'b0001;
    end
endmodule

multiplexers/16to1/mux16to1_tb.vcd
$date
	Mon Jul 26 20:01:46 2021
$end
$version
	Icarus Verilog
$end
$timescale
	1ns
$end
$scope module decoder_tb $end
$var reg 16 ! a_t [15:0] $end
$upscope $end
$scope module decoder_tb $end
$var reg 4 " sel_t [3:0] $end
$upscope $end
$scope module decoder_tb $end
$var reg 1 # enable_t $end
$upscope $end
$scope module decoder_tb $end
$var wire 1 $ y_t $end
$upscope $end
$enddefinitions $end
#0
$dumpvars
0$
0#
b0 "
b1011011100110111 !
$end
#10
1$
1#
#20
b1 "
#30
1$
b10 "
#40
0$
b11 "
#50
1$
b100 "
#60
b101 "
#70
0$
b110 "
#80
b111 "
#90
1$
b1000 "
#100
b1001 "
#110
1$
b1010 "
#120
0$
b1011 "
#130
1$
b1100 "
#140
b1101 "
#150
0$
b1110 "
#160
1$
b1111 "
