Arithmetic_Circuits/Byte_Adder/byteadder.v
`timescale 1ns/1ns

module half_adder (A,B,S,C);
    input A;
    input B;
    output S;
    output C;
    
    assign S = A^B;
    assign C = A & B;
    
endmodule

module full_adder (
    input A,B,Cin,
    output S,Cout
    
);
wire C0,S0,C1;
half_adder H1(A,B,S0,C0);
half_adder H2(Cin,S0,S,C1);
assign Cout = C0|C1;

    
endmodule


module fourbitadder (
    input[3:0] addent,augend,
    input cin,
    output[3:0] s,
    output cout
);
    wire[2:0] cintermed;
    full_adder F1(.A(addent[0]),.B(augend[0]),.Cin(cin),.S(s[0]),.Cout(cintermed[0]));
    full_adder F2(.A(addent[1]),.B(augend[1]),.Cin(cintermed[0]),.S(s[1]),.Cout(cintermed[1]));
    full_adder F3(.A(addent[2]),.B(augend[2]),.Cin(cintermed[1]),.S(s[2]),.Cout(cintermed[2]));
    full_adder F4(.A(addent[3]),.B(augend[3]),.Cin(cintermed[2]),.S(s[3]),.Cout(cout));
endmodule

module byteadder (
    input[7:0] addent,augend,
    input cin,
    output[7:0] s,
    output cout
);
    wire c0;
    fourbitadder X1(.addent(addent[3:0]),.augend(augend[3:0]),.cin(cin),.s(s[3:0]),.cout(c0));
    fourbitadder X2(.addent(addent[7:4]),.augend(augend[7:4]),.cin(c0),.s(s[7:4]),.cout(cout));   
endmodule

Arithmetic_Circuits/Byte_Adder/byteadder_tb.v
`include "byteadder.v"
`timescale 1ns/1ns

module byteadder_tb ();

reg[7:0] addent_t,augend_t;
reg cin_t;
wire[7:0] s_t;
wire cout_t;
byteadder F1(.addent(addent_t),.augend(augend_t),.cin(cin_t),.s(s_t),.cout(cout_t));
initial begin
   $dumpfile("byteadder_tb.vcd");
   $dumpvars(1,addent_t,augend_t,cin_t,s_t,cout_t);
   $monitor("%0d %0d %0d %0d %0d",addent_t,augend_t,cin_t,s_t,cout_t);
   cin_t = 1'b0;
   addent_t = 8'b1000_0001;
   augend_t = 8'b0000_0000;
   repeat(45)
    #10 augend_t = augend_t + 8'b0000_0010;

end
    
endmodule

Arithmetic_Circuits/Byte_Adder/byteadder_tb.vcd
$date
	Thu Jul 29 22:47:14 2021
$end
$version
	Icarus Verilog
$end
$timescale
	1ns
$end
$scope module byteadder_tb $end
$var reg 8 ! addent_t [7:0] $end
$upscope $end
$scope module byteadder_tb $end
$var reg 8 " augend_t [7:0] $end
$upscope $end
$scope module byteadder_tb $end
$var reg 1 # cin_t $end
$upscope $end
$scope module byteadder_tb $end
$var wire 8 $ s_t [7:0] $end
$upscope $end
$scope module byteadder_tb $end
$var wire 1 % cout_t $end
$upscope $end
$enddefinitions $end
#0
$dumpvars
0%
b10000001 $
0#
b0 "
b10000001 !
$end
#10
b10000011 $
b10 "
#20
b10000101 $
b100 "
#30
b10000111 $
b110 "
#40
b10001001 $
b1000 "
#50
b10001011 $
b1010 "
#60
b10001101 $
b1100 "
#70
b10001111 $
b1110 "
#80
b10010001 $
b10000 "
#90
b10010011 $
b10010 "
#100
b10010101 $
b10100 "
#110
b10010111 $
b10110 "
#120
b10011001 $
b11000 "
#130
b10011011 $
b11010 "
#140
b10011101 $
b11100 "
#150
b10011111 $
b11110 "
#160
b10100001 $
b100000 "
#170
b10100011 $
b100010 "
#180
b10100101 $
b100100 "
#190
b10100111 $
b100110 "
#200
b10101001 $
b101000 "
#210
b10101011 $
b101010 "
#220
b10101101 $
b101100 "
#230
b10101111 $
b101110 "
#240
b10110001 $
b110000 "
#250
b10110011 $
b110010 "
#260
b10110101 $
b110100 "
#270
b10110111 $
b110110 "
#280
b10111001 $
b111000 "
#290
b10111011 $
b111010 "
#300
b10111101 $
b111100 "
#310
b10111111 $
b111110 "
#320
b11000001 $
b1000000 "
#330
b11000011 $
b1000010 "
#340
b11000101 $
b1000100 "
#350
b11000111 $
b1000110 "
#360
b11001001 $
b1001000 "
#370
b11001011 $
b1001010 "
#380
b11001101 $
b1001100 "
#390
b11001111 $
b1001110 "
#400
b11010001 $
b1010000 "
#410
b11010011 $
b1010010 "
#420
b11010101 $
b1010100 "
#430
b11010111 $
b1010110 "
#440
b11011001 $
b1011000 "
#450
b11011011 $
b1011010 "
