decoder/decoder.v
`timescale 1ns/1ns

module decoder (
    input [3:0]sel,
    input enable,
    output [15:0]D
);
    wire [3:0]sel_not;
    assign sel_not= ~sel;
    nand (D[0],sel_not[0],sel_not[1],sel_not[2],sel_not[3],enable);
    nand (D[1],sel[0],sel_not[1],sel_not[2],sel_not[3],enable);
    nand (D[2],sel_not[0],sel[1],sel_not[2],sel_not[3],enable);
    nand (D[3],sel[0],sel[1],sel_not[2],sel_not[3],enable);
    
    nand (D[4],sel_not[0],sel_not[1],sel[2],sel_not[3],enable);
    nand (D[5],sel[0],sel_not[1],sel[2],sel_not[3],enable);
    nand (D[6],sel_not[0],sel[1],sel[2],sel_not[3],enable);
    nand (D[7],sel[0],sel[1],sel[2],sel_not[3],enable);
    
    nand (D[8],sel_not[0],sel_not[1],sel_not[2],sel[3],enable);
    nand (D[9],sel[0],sel_not[1],sel_not[2],sel[3],enable);
    nand (D[10],sel_not[0],sel[1],sel_not[2],sel[3],enable);
    nand (D[11],sel[0],sel[1],sel_not[2],sel[3],enable);
    
    nand (D[12],sel_not[0],sel_not[1],sel[2],sel[3],enable);
    nand (D[13],sel[0],sel_not[1],sel[2],sel[3],enable);
    nand (D[14],sel_not[0],sel[1],sel[2],sel[3],enable);
    nand (D[15],sel[0],sel[1],sel[2],sel[3],enable);
    
endmodule

decoder/decoder_tb.v
`timescale 1ns/1ns
`include "decoder.v"

module decoder_tb ();
    reg [3:0]sel_t;
    reg enable_t;
    wire [15:0]d_t;
    decoder uut(.sel(sel_t),.enable(enable_t),.D(d_t));
    initial begin
        $dumpfile("decoder_tb.vcd");
        $dumpvars(1,sel_t,enable_t,d_t);
        $monitor("%b %b",sel_t,d_t);
        sel_t = 4'b0000;
        enable_t = 1'b0;
        #10 enable_t = 1'b1;
        sel_t = 4'b0000;
        repeat(15)
        #10 sel_t = sel_t + 4'b0001;
    end
endmodule

decoder/decoder_tb.vcd
$date
	Mon Jul 26 19:21:11 2021
$end
$version
	Icarus Verilog
$end
$timescale
	1ns
$end
$scope module decoder_tb $end
$var reg 4 ! sel_t [3:0] $end
$upscope $end
$scope module decoder_tb $end
$var reg 1 " enable_t $end
$upscope $end
$scope module decoder_tb $end
$var wire 16 # d_t [15:0] $end
$upscope $end
$enddefinitions $end
#0
$dumpvars
b1111111111111111 #
0"
b0 !
$end
#10
b1111111111111110 #
1"
#20
b1111111111111101 #
b1 !
#30
b1111111111111011 #
b10 !
#40
b1111111111110111 #
b11 !
#50
b1111111111101111 #
b100 !
#60
b1111111111011111 #
b101 !
#70
b1111111110111111 #
b110 !
#80
b1111111101111111 #
b111 !
#90
b1111111011111111 #
b1000 !
#100
b1111110111111111 #
b1001 !
#110
b1111101111111111 #
b1010 !
#120
b1111011111111111 #
b1011 !
#130
b1110111111111111 #
b1100 !
#140
b1101111111111111 #
b1101 !
#150
b1011111111111111 #
b1110 !
#160
b111111111111111 #
b1111 !
