Arithmetic_Circuits/Nibble_Adder/fourbitadder.v
`timescale 1ns/1ns

module half_adder (A,B,S,C);
    input A;
    input B;
    output S;
    output C;
    
    assign S = A^B;
    assign C = A & B;
    
endmodule

module full_adder (
    input A,B,Cin,
    output S,Cout
    
);
wire C0,S0,C1;
half_adder H1(A,B,S0,C0);
half_adder H2(Cin,S0,S,C1);
assign Cout = C0|C1;

    
endmodule


module fourbitadder (
    input[3:0] addent,augend,
    input cin,
    output[3:0] s,
    output cout
);
    wire[2:0] cintermed;
    full_adder F1(.A(addent[0]),.B(augend[0]),.Cin(cin),.S(s[0]),.Cout(cintermed[0]));
    full_adder F2(.A(addent[1]),.B(augend[1]),.Cin(cintermed[0]),.S(s[1]),.Cout(cintermed[1]));
    full_adder F3(.A(addent[2]),.B(augend[2]),.Cin(cintermed[1]),.S(s[2]),.Cout(cintermed[2]));
    full_adder F4(.A(addent[3]),.B(augend[3]),.Cin(cintermed[2]),.S(s[3]),.Cout(cout));
endmodule

Arithmetic_Circuits/Nibble_Adder/fourbitadder_tb.v
`include "fourbitadder.v"
`timescale 1ns/1ns

module fourbitadder_tb ();

reg[3:0] addent_t,augend_t;
reg cin_t;
wire[3:0] s_t;
wire cout_t;
fourbitadder F1(.addent(addent_t),.augend(augend_t),.cin(cin_t),.s(s_t),.cout(cout_t));
initial begin
   $dumpfile("fourbitadder_tb.vcd");
   $dumpvars(1,addent_t,augend_t,cin_t,s_t,cout_t);
   $monitor("%0d %0d %0d %0d %0d",addent_t,augend_t,cin_t,s_t,cout_t);
   cin_t = 1'b1;
   addent_t = 4'b1111;
   augend_t = 4'b0000;
   repeat(15)
    #10 augend_t = augend_t + 4'b0001;

end
    
endmodule

Arithmetic_Circuits/Nibble_Adder/fourbitadder_tb.vcd
$date
	Thu Jul 29 21:55:33 2021
$end
$version
	Icarus Verilog
$end
$timescale
	1ns
$end
$scope module fourbitadder_tb $end
$var reg 4 ! addent_t [3:0] $end
$upscope $end
$scope module fourbitadder_tb $end
$var reg 4 " augend_t [3:0] $end
$upscope $end
$scope module fourbitadder_tb $end
$var reg 1 # cin_t $end
$upscope $end
$scope module fourbitadder_tb $end
$var wire 4 $ s_t [3:0] $end
$upscope $end
$scope module fourbitadder_tb $end
$var wire 1 % cout_t $end
$upscope $end
$enddefinitions $end
#0
$dumpvars
1%
b0 $
1#
b0 "
b1111 !
$end
#10
b1 $
b1 "
#20
b10 $
b10 "
#30
b11 $
b11 "
#40
b100 $
b100 "
#50
b101 $
b101 "
#60
b110 $
b110 "
#70
b111 $
b111 "
#80
b1000 $
b1000 "
#90
b1001 $
b1001 "
#100
b1010 $
b1010 "
#110
b1011 $
b1011 "
#120
b1100 $
b1100 "
#130
b1101 $
b1101 "
#140
b1110 $
b1110 "
#150
b1111 $
b1111 "
